setup.py
opensource/__init__.py
opensource.egg-info/PKG-INFO
opensource.egg-info/SOURCES.txt
opensource.egg-info/dependency_links.txt
opensource.egg-info/requires.txt
opensource.egg-info/top_level.txt
opensource/licenses/__init__.py
opensource/licenses/wrapper.py