Metadata-Version: 1.0
Name: opensource
Version: 1.0.2
Summary: Query the Open Source License API
Home-page: UNKNOWN
Author: Paul Tagliamonte
Author-email: paultag@opensource.org
License: MIT
Platform: any
